CHANGELOG.rst
MANIFEST.in
README.rst
setup.py
test-config.py
SpanishAcquisition.egg-info/PKG-INFO
SpanishAcquisition.egg-info/SOURCES.txt
SpanishAcquisition.egg-info/dependency_links.txt
SpanishAcquisition.egg-info/top_level.txt
examples/__init__.py
examples/acquisition.py
examples/data_explorer.py
spacq/__init__.py
spacq/devices/__init__.py
spacq/devices/abstract_device.py
spacq/devices/config.py
spacq/devices/tools.py
spacq/devices/agilent/__init__.py
spacq/devices/agilent/dm34410a.py
spacq/devices/agilent/mock/__init__.py
spacq/devices/agilent/mock/mock_dm34410a.py
spacq/devices/agilent/mock/tests/__init__.py
spacq/devices/agilent/mock/tests/test_mock_dm34410a.py
spacq/devices/agilent/tests/__init__.py
spacq/devices/agilent/tests/server/__init__.py
spacq/devices/agilent/tests/server/test_dm34410a.py
spacq/devices/iqc/__init__.py
spacq/devices/iqc/voltage_source.py
spacq/devices/iqc/gui/__init__.py
spacq/devices/iqc/gui/voltage_source.py
spacq/devices/iqc/mock/__init__.py
spacq/devices/iqc/mock/mock_voltage_source.py
spacq/devices/iqc/mock/tests/__init__.py
spacq/devices/iqc/mock/tests/test_mock_voltage_source.py
spacq/devices/iqc/tests/__init__.py
spacq/devices/iqc/tests/test_voltage_source.py
spacq/devices/iqc/tests/server/__init__.py
spacq/devices/iqc/tests/server/test_voltage_source.py
spacq/devices/mock/__init__.py
spacq/devices/mock/mock_abstract_device.py
spacq/devices/mock/tests/__init__.py
spacq/devices/mock/tests/test_mock_abstract_device.py
spacq/devices/oxford/__init__.py
spacq/devices/oxford/ips120_10.py
spacq/devices/oxford/mock/__init__.py
spacq/devices/oxford/mock/mock_ips120_10.py
spacq/devices/oxford/mock/tests/__init__.py
spacq/devices/oxford/mock/tests/test_mock_ips120_10.py
spacq/devices/oxford/tests/__init__.py
spacq/devices/oxford/tests/server/__init__.py
spacq/devices/oxford/tests/server/test_ips120_10.py
spacq/devices/rohde_schwarz/__init__.py
spacq/devices/rohde_schwarz/smf100a.py
spacq/devices/rohde_schwarz/mock/__init__.py
spacq/devices/rohde_schwarz/mock/mock_smf100a.py
spacq/devices/rohde_schwarz/mock/tests/__init__.py
spacq/devices/rohde_schwarz/mock/tests/test_mock_smf100a.py
