Metadata-Version: 1.0
Name: SpanishAcquisition
Version: 1.0.3
Summary: Package for interfacing with devices and building user interfaces.
Home-page: http://0.github.com/SpanishAcquisition/
Author: Dmitri Iouchtchenko
Author-email: diouchtc@uwaterloo.ca
License: BSD
Platform: UNKNOWN
Classifier: Development Status :: 5 - Production/Stable
Classifier: Intended Audience :: Science/Research
Classifier: License :: OSI Approved :: BSD License
Classifier: Operating System :: OS Independent
Classifier: Programming Language :: Python :: 2
